{
  "dvdid": "FC2-718323",
  "cid": null,
  "plot": null,
  "cover": "https://storage52000.contents.fc2.com/file/315/31464497/1598506087.3.jpg",
  "big_cover": null,
  "genre": [
    "人妻",
    "ハメ撮り",
    "中出し",
    "個人撮影",
    "オリジナル",
    "無修正",
    "寝取られ",
    "美人",
    "可愛い",
    "生ハメ"
  ],
  "genre_id": null,
  "genre_norm": null,
  "score": "9.85",
  "title": "【個人撮影】破壊力抜群のデカケツ美人妻れいなさんと再戦そして大量中出し【背徳の制服編】",
  "ori_title": null,
  "magnet": null,
  "serial": null,
  "actress": null,
  "actress_pics": null,
  "director": null,
  "duration": "78",
  "producer": "EX-STANDARD",
  "publisher": null,
  "uncensored": null,
  "publish_date": "2017-11-30",
  "preview_pics": [
    "https://storage52000.contents.fc2.com/file/315/31464497/1598506087.3.jpg",
    "https://storage52000.contents.fc2.com/file/315/31464497/1598506087.57.jpg",
    "https://storage52000.contents.fc2.com/file/315/31464497/1598506087.83.jpg",
    "https://storage52000.contents.fc2.com/file/315/31464497/1598506088.09.jpg",
    "https://storage52000.contents.fc2.com/file/315/31464497/1598506088.36.jpg",
    "https://storage52000.contents.fc2.com/file/315/31464497/1598506088.62.jpg",
    "https://storage52000.contents.fc2.com/file/315/31464497/1598506088.88.jpg",
    "https://storage52000.contents.fc2.com/file/315/31464497/1598506089.16.jpg",
    "https://storage52000.contents.fc2.com/file/315/31464497/1598506089.42.jpg",
    "https://storage52000.contents.fc2.com/file/315/31464497/1598506089.68.jpg"
  ],
  "preview_video": "https://vip-videoprem49000.fc2.com/up/201711/29/L/4/cut20171129L0ACggL4.mp4?mid=a21a226ab188e99c9647823a4caf3775"
}